app/__main__.py
app/config.py
app/hass.py
app/run.py
app/server.py
hass_mcp_li-0.1.3.dist-info/METADATA
hass_mcp_li-0.1.3.dist-info/WHEEL
hass_mcp_li-0.1.3.dist-info/entry_points.txt
hass_mcp_li-0.1.3.dist-info/licenses/LICENSE
hass_mcp_li-0.1.3.dist-info/RECORD
