Metadata-Version: 2.4
Name: hass-mcp-li
Version: 0.1.3
Summary: Home Assistant Model Context Protocol (MCP) server
License-File: LICENSE
Requires-Python: >=3.13
Requires-Dist: httpx>=0.27.0
Requires-Dist: mcp[cli]>=1.4.1
Provides-Extra: test
Requires-Dist: pytest-asyncio>=0.24.0; extra == 'test'
Requires-Dist: pytest>=8.3.5; extra == 'test'
